cli/__init__.py
cli/meow.py
ria/Cat.py
ria/__init__.py
ria-0.1.1.dist-info/LICENSE
ria-0.1.1.dist-info/METADATA
ria-0.1.1.dist-info/WHEEL
ria-0.1.1.dist-info/entry_points.txt
ria-0.1.1.dist-info/top_level.txt
ria-0.1.1.dist-info/RECORD
