Metadata-Version: 2.1
Name: ria
Version: 0.1.1
Summary: Radio Intelligence Apps' open-source core, by Qoherent
Author-email: "Qoherent Inc." <info@qoherent.ai>
Maintainer-email: Michael Luciuk <michael@qoherent.ai>, Ashkan Beigi <ash@qoherent.ai>
License: GNU GENERAL PUBLIC LICENSE
Project-URL: Qoherent, https://www.qoherent.ai/
Project-URL: Documentation, https://readthedocs.org
Project-URL: Source, https://github.com/mrl280/ria
Project-URL: Issues, https://github.com/mrl280/ria/issues
Keywords: radio,machine learning
Classifier: Development Status :: 2 - Pre-Alpha
Classifier: Programming Language :: Python :: 3
Classifier: Intended Audience :: Science/Research
Classifier: License :: OSI Approved :: GNU General Public License v3 (GPLv3)
Classifier: Natural Language :: English
Classifier: Operating System :: OS Independent
Classifier: Topic :: Scientific/Engineering :: Artificial Intelligence
Classifier: Typing :: Typed
Requires-Python: >=3.11
License-File: LICENSE
